AUTHORS.rst
CONTRIBUTING.rst
HISTORY.rst
LICENSE
MANIFEST.in
README.rst
setup.cfg
setup.py
django_eulasees/__init__.py
django_eulasees/admin.py
django_eulasees/api.py
django_eulasees/models.py
django_eulasees/serializers.py
django_eulasees/urls.py
django_eulasees.egg-info/PKG-INFO
django_eulasees.egg-info/SOURCES.txt
django_eulasees.egg-info/dependency_links.txt
django_eulasees.egg-info/not-zip-safe
django_eulasees.egg-info/top_level.txt
django_eulasees/migrations/0001_initial.py
django_eulasees/migrations/0002_auto_20141206_1419.py
django_eulasees/migrations/0003_auto_20141207_1322.py
django_eulasees/migrations/__init__.py
django_eulasees/static/css/django_eulasees.css
django_eulasees/static/js/django_eulasees.js
django_eulasees/templates/django_eulasees/base.html