Metadata-Version: 1.1
Name: django-eulasees
Version: 0.2.5
Summary: Team Bermuda django app for koding hackathon
Home-page: https://github.com/swfiua/django_eulasees
Author: Johnny Gill
Author-email: swfiua@gmail.com
License: BSD
Keywords: django_eulasees
Platform: UNKNOWN
Classifier: Development Status :: 2 - Pre-Alpha
Classifier: Framework :: Django
Classifier: Intended Audience :: Developers
Classifier: License :: OSI Approved :: BSD License
Classifier: Natural Language :: English
Classifier: Programming Language :: Python :: 2
Classifier: Programming Language :: Python :: 2.6
Classifier: Programming Language :: Python :: 2.7
Classifier: Programming Language :: Python :: 3
Classifier: Programming Language :: Python :: 3.3
